{
    "chapter": [
        {
            "testament": "NT",
            "book": "Mark",
            "chapter": "12",
            "textSrc": "GOC",
            "language": "Greek",
            "verseNum": 0,
            "cueNdx": 0,
            "cueTime": 0,
            "cueText": "Introduction to Mark 12"
        },
        {
            "testament": "NT",
            "book": "Mark",
            "chapter": "12",
            "textSrc": "GOC",
            "language": "Greek",
            "verseNum": 1,
            "cueNdx": 1,
            "cueTime": 3903,
            "cueText": " Καὶ ἤρξατο αὐτοῖς ἐν παραβολαῖς λέγεῖν ἀμπελῶνα ἐφύτευσεν ἄνθρωπος καὶ περιέθηκε φραγμὸν καὶ ὤρυξεν ὑπολήνιον καὶ ᾠκοδόμησε πύργον, καὶ ἐξέδοτο αὐτὸν γεωργοῖς καὶ ἀπεδήμησε\r\n"
        },
        {
            "testament": "NT",
            "book": "Mark",
            "chapter": "12",
            "textSrc": "GOC",
            "language": "Greek",
            "verseNum": 2,
            "cueNdx": 2,
            "cueTime": 16812,
            "cueText": " καὶ ἀπέστειλε πρὸς τοὺς γεωργοὺς τῷ καιρῷ δοῦλον, ἵνα παρὰ τῶν γεωργῶν λάβῃ ἀπὸ τοῦ καρποῦ τοῦ ἀμπελῶνος\r\n"
        },
        {
            "testament": "NT",
            "book": "Mark",
            "chapter": "12",
            "textSrc": "GOC",
            "language": "Greek",
            "verseNum": 3,
            "cueNdx": 3,
            "cueTime": 23857,
            "cueText": " καὶ λαβόντες αὐτὸν ἔδειραν καὶ ἀπέστειλαν κενόν\r\n"
        },
        {
            "testament": "NT",
            "book": "Mark",
            "chapter": "12",
            "textSrc": "GOC",
            "language": "Greek",
            "verseNum": 4,
            "cueNdx": 4,
            "cueTime": 28446,
            "cueText": " καὶ πάλιν ἀπέστειλε πρὸς αὐτοὺς ἄλλον δοῦλον κἀκεῖνον λιθοβολήσαντες ἐκεφαλαίωσαν καὶ ἀπέστειλαν ἠτιμωμένον\r\n"
        },
        {
            "testament": "NT",
            "book": "Mark",
            "chapter": "12",
            "textSrc": "GOC",
            "language": "Greek",
            "verseNum": 5,
            "cueNdx": 5,
            "cueTime": 36402,
            "cueText": " καὶ πάλιν ἄλλον ἀπέστειλε κἀκεῖνον ἀπέκτειναν, καὶ πολλοὺς ἄλλους, οὓς μὲν δέροντες, οὓς δὲ ἀποκτέννοντες\r\n"
        },
        {
            "testament": "NT",
            "book": "Mark",
            "chapter": "12",
            "textSrc": "GOC",
            "language": "Greek",
            "verseNum": 6,
            "cueNdx": 6,
            "cueTime": 44884,
            "cueText": " ἔτι οὖν ἕνα υἱὸν ἔχων, ἀγαπητὸν αὐτοῦ, ἀπέστειλε καὶ αὐτὸν ἔσχατον πρὸς αὐτοὺς λέγων ὅτι ἐντραπήσονται τὸν υἱόν μου\r\n"
        },
        {
            "testament": "NT",
            "book": "Mark",
            "chapter": "12",
            "textSrc": "GOC",
            "language": "Greek",
            "verseNum": 7,
            "cueNdx": 7,
            "cueTime": 54341,
            "cueText": " ἐκεῖνοι δὲ οἱ γεωργοί, θεασάμενοι αὐτὸν ἐρχόμενον, πρὸς ἑαυτοὺς εἶπον ὅτι οὗτός ἐστιν ὁ κληρονόμος δεῦτε ἀποκτείνωμεν αὐτόν, καὶ ἡμῶν ἔσται ἡ κληρονομία\r\n"
        },
        {
            "testament": "NT",
            "book": "Mark",
            "chapter": "12",
            "textSrc": "GOC",
            "language": "Greek",
            "verseNum": 8,
            "cueNdx": 8,
            "cueTime": 65447,
            "cueText": " καὶ λαβόντες ἀπέκτειναν καὶ ἐξέβαλον αὐτὸν ἔξω τοῦ ἀμπελῶνος\r\n"
        },
        {
            "testament": "NT",
            "book": "Mark",
            "chapter": "12",
            "textSrc": "GOC",
            "language": "Greek",
            "verseNum": 9,
            "cueNdx": 9,
            "cueTime": 70778,
            "cueText": " τί οὖν ποιήσει ὁ κύριος τοῦ ἀμπελῶνος; ἐλεύσεται καὶ ἀπολέσει τοὺς γεωργοὺς τούτους, καὶ δώσει τὸν ἀμπελῶνα ἄλλοις\r\n"
        },
        {
            "testament": "NT",
            "book": "Mark",
            "chapter": "12",
            "textSrc": "GOC",
            "language": "Greek",
            "verseNum": 10,
            "cueNdx": 10,
            "cueTime": 80085,
            "cueText": " οὐδὲ τὴν γραφὴν ταύτην ἀνέγνωτε, λίθον ὃν ἀπεδοκίμασαν οἱ οἰκοδομοῦντες, οὗτος ἐγενήθη εἰς κεφαλὴν γωνίας\r\n"
        },
        {
            "testament": "NT",
            "book": "Mark",
            "chapter": "12",
            "textSrc": "GOC",
            "language": "Greek",
            "verseNum": 11,
            "cueNdx": 11,
            "cueTime": 89220,
            "cueText": " παρὰ Κυρίου ἐγένετο αὕτη, καὶ ἔστι θαυμαστὴ ἐν ὀφθαλμοῖς ἡμῶν;\r\n"
        },
        {
            "testament": "NT",
            "book": "Mark",
            "chapter": "12",
            "textSrc": "GOC",
            "language": "Greek",
            "verseNum": 12,
            "cueNdx": 12,
            "cueTime": 93991,
            "cueText": " καὶ ἐζήτουν αὐτὸν κρατῆσαι, καὶ ἐφοβήθησαν τὸν ὄχλον ἔγνωσαν γὰρ ὅτι πρὸς αὐτοὺς τὴν παραβολὴν εἶπε καὶ ἀφέντες αὐτὸν ἀπῆλθον\r\n"
        },
        {
            "testament": "NT",
            "book": "Mark",
            "chapter": "12",
            "textSrc": "GOC",
            "language": "Greek",
            "verseNum": 13,
            "cueNdx": 13,
            "cueTime": 104929,
            "cueText": " Καὶ ἀποστέλλουσι πρὸς αὐτόν τινας τῶν Φαρισαίων καὶ τῶν Ἡρῳδιανῶν ἵνα αὐτὸν ἀγρεύσωσι λόγῳ\r\n"
        },
        {
            "testament": "NT",
            "book": "Mark",
            "chapter": "12",
            "textSrc": "GOC",
            "language": "Greek",
            "verseNum": 14,
            "cueNdx": 14,
            "cueTime": 112283,
            "cueText": " οἱ δὲ ἐλθόντες λέγουσιν αὐτῷ διδάσκαλε, οἴδαμεν ὅτι ἀληθὴς εἶ καὶ οὐ μέλει σοι περὶ οὐδενός οὐ γὰρ βλέπεις εἰς πρόσωπον ἀνθρώπων, ἀλλ᾽ ἐπ᾽ ἀληθείας τὴν ὁδὸν τοῦ Θεοῦ διδάσκεις εἰπὲ οὖν ἡμῖν ἔξεστι δοῦναι κῆνσον Καίσαρι ἢ οὔ; δῶμεν ἢ μὴ δῶμεν;\r\n"
        },
        {
            "testament": "NT",
            "book": "Mark",
            "chapter": "12",
            "textSrc": "GOC",
            "language": "Greek",
            "verseNum": 15,
            "cueNdx": 15,
            "cueTime": 134424,
            "cueText": " ὁ δὲ εἰδὼς αὐτῶν τὴν ὑπόκρισιν εἶπεν αὐτοῖς τί με πειράζετε; φέρετέ μοι δηνάριον ἵνα ἴδω\r\n"
        },
        {
            "testament": "NT",
            "book": "Mark",
            "chapter": "12",
            "textSrc": "GOC",
            "language": "Greek",
            "verseNum": 16,
            "cueNdx": 16,
            "cueTime": 142380,
            "cueText": " οἱ δὲ ἤνεγκαν καὶ λέγει αὐτοῖς τίνος ἡ εἰκὼν αὕτη καὶ ἡ ἐπιγραφή; οἱ δὲ εἶπον Καίσαρος\r\n"
        },
        {
            "testament": "NT",
            "book": "Mark",
            "chapter": "12",
            "textSrc": "GOC",
            "language": "Greek",
            "verseNum": 17,
            "cueNdx": 17,
            "cueTime": 151387,
            "cueText": " καὶ ἀποκριθεὶς ὁ Ἰησοῦς εἶπεν αὐτοῖς ἀπόδοτε τὰ Καίσαρος Καίσαρι καὶ τὰ τοῦ Θεοῦ τῷ Θεῷ καὶ ἐθαύμασαν ἐπ᾽ αὐτῷ\r\n"
        },
        {
            "testament": "NT",
            "book": "Mark",
            "chapter": "12",
            "textSrc": "GOC",
            "language": "Greek",
            "verseNum": 18,
            "cueNdx": 18,
            "cueTime": 161594,
            "cueText": " Καὶ ἔρχονται Σαδδουκαῖοι πρὸς αὐτόν, οἵτινες λέγουσιν ἀνάστασιν μὴ εἶναι, καὶ ἐπηρώτων αὐτὸν λέγοντες\r\n"
        },
        {
            "testament": "NT",
            "book": "Mark",
            "chapter": "12",
            "textSrc": "GOC",
            "language": "Greek",
            "verseNum": 19,
            "cueNdx": 19,
            "cueTime": 169625,
            "cueText": " διδάσκαλε, Μωϋσῆς ἔγραψεν ἡμῖν ὅτι ἐάν τινος ἀδελφὸς ἀποθάνῃ καὶ καταλίπῃ γυναῖκα, καὶ τέκνα μὴ ἀφῇ, ἵνα λάβῃ ὁ ἀδελφὸς αὐτοῦ τὴν γυναῖκα αὐτοῦ καὶ ἐξαναστήσῃ σπέρμα τῷ ἀδελφῷ αὐτοῦ\r\n"
        },
        {
            "testament": "NT",
            "book": "Mark",
            "chapter": "12",
            "textSrc": "GOC",
            "language": "Greek",
            "verseNum": 20,
            "cueNdx": 20,
            "cueTime": 182569,
            "cueText": " ἑπτὰ οὖν ἀδελφοὶ ἦσαν καὶ ὁ πρῶτος ἔλαβε γυναῖκα, καὶ ἀποθνήσκων οὐκ ἀφῆκε σπέρμα\r\n"
        },
        {
            "testament": "NT",
            "book": "Mark",
            "chapter": "12",
            "textSrc": "GOC",
            "language": "Greek",
            "verseNum": 21,
            "cueNdx": 21,
            "cueTime": 189121,
            "cueText": " καὶ ὁ δεύτερος ἔλαβεν αὐτήν, καὶ ἀπέθανε, καὶ οὐδὲ αὐτὸς οὐκ ἀφῆκε σπέρμα καὶ ὁ τρίτος ὡσαύτως\r\n"
        },
        {
            "testament": "NT",
            "book": "Mark",
            "chapter": "12",
            "textSrc": "GOC",
            "language": "Greek",
            "verseNum": 22,
            "cueNdx": 22,
            "cueTime": 196079,
            "cueText": " καὶ ἔλαβον αὐτὴν οἱ ἑπτὰ, καὶ οὐκ ἀφῆκαν σπέρμα ἐσχάτη πάντων ἀπέθανε καὶ ἡ γυνή\r\n"
        },
        {
            "testament": "NT",
            "book": "Mark",
            "chapter": "12",
            "textSrc": "GOC",
            "language": "Greek",
            "verseNum": 23,
            "cueNdx": 23,
            "cueTime": 202009,
            "cueText": " ἐν τῇ οὖν ἀναστάσει, ὅταν ἀναστῶσι, τίνος αὐτῶν ἔσται γυνή; οἱ γὰρ ἑπτὰ ἔσχον αὐτὴν γυναῖκα\r\n"
        },
        {
            "testament": "NT",
            "book": "Mark",
            "chapter": "12",
            "textSrc": "GOC",
            "language": "Greek",
            "verseNum": 24,
            "cueNdx": 24,
            "cueTime": 209439,
            "cueText": " καὶ ἀποκριθεὶς ὁ Ἰησοῦς εἶπεν αὐτοῖς οὐ διὰ τοῦτο πλανᾶσθε μὴ εἰδότες τὰς γραφὰς μηδὲ τὴν δύναμιν τοῦ Θεοῦ;\r\n"
        },
        {
            "testament": "NT",
            "book": "Mark",
            "chapter": "12",
            "textSrc": "GOC",
            "language": "Greek",
            "verseNum": 25,
            "cueNdx": 25,
            "cueTime": 218896,
            "cueText": " ὅταν γὰρ ἐκ νεκρῶν ἀναστῶσιν, οὔτε γαμοῦσιν οὔτε γαμίζονται, ἀλλ᾽ εἰσὶν ὡς ἄγγελοι οἱ ἐν τοῖς οὐρανοῖς\r\n"
        },
        {
            "testament": "NT",
            "book": "Mark",
            "chapter": "12",
            "textSrc": "GOC",
            "language": "Greek",
            "verseNum": 26,
            "cueNdx": 26,
            "cueTime": 227078,
            "cueText": " περὶ δὲ τῶν νεκρῶν ὅτι ἐγείρονται, οὐκ ἀνέγνωτε ἐν τῇ βίβλῳ Μωϋσέως, ἐπὶ του βάτου πως εἶπεν αὐτῷ ὁ Θεὸς λέγων ἐγὼ ὁ Θεὸς Ἀβραὰμ καὶ ὁ Θεὸς Ἰσαὰκ καὶ ὁ Θεὸς Ἰακώβ;\r\n"
        },
        {
            "testament": "NT",
            "book": "Mark",
            "chapter": "12",
            "textSrc": "GOC",
            "language": "Greek",
            "verseNum": 27,
            "cueNdx": 27,
            "cueTime": 239560,
            "cueText": " οὐκ ἔστιν ὁ Θεὸς νεκρῶν, ἀλλὰ ζώντων ὑμεῖς οὖν πολὺ πλανᾶσθε\r\n"
        },
        {
            "testament": "NT",
            "book": "Mark",
            "chapter": "12",
            "textSrc": "GOC",
            "language": "Greek",
            "verseNum": 28,
            "cueNdx": 28,
            "cueTime": 244941,
            "cueText": " Καὶ προσελθὼν εἷς τῶν γραμματέων ἀκούσας αὐτῶν συζητούντων, ἰδὼν ὅτι καλῶς αὐτοῖς ἀπεκρίθη, ἐπηρώτησεν αὐτόν ποία ἐστὶ πρώτη πάντων ἐντολή;\r\n"
        },
        {
            "testament": "NT",
            "book": "Mark",
            "chapter": "12",
            "textSrc": "GOC",
            "language": "Greek",
            "verseNum": 29,
            "cueNdx": 29,
            "cueTime": 256500,
            "cueText": " ὁ δὲ Ἰησοῦς ἀπεκρίθη αὐτῷ ὅτι πρώτη πάντῶν ἐντολή ἄκουε, Ἰσραήλ, Κύριος ὁ Θεὸς ἡμῶν Κύριος εἷς ἐστι\r\n"
        },
        {
            "testament": "NT",
            "book": "Mark",
            "chapter": "12",
            "textSrc": "GOC",
            "language": "Greek",
            "verseNum": 30,
            "cueNdx": 30,
            "cueTime": 267608,
            "cueText": " καὶ ἀγαπήσεις Κύριον τὸν Θεόν σου ἐξ ὅλης τῆς καρδίας σου καὶ ἐξ ὅλης τῆς ψυχῆς σου καὶ ἐξ ὅλης τῆς διανοίας σου καὶ ἐξ ὅλης τῆς ἰσχύος σου αὕτη πρώτη ἐντολή\r\n"
        },
        {
            "testament": "NT",
            "book": "Mark",
            "chapter": "12",
            "textSrc": "GOC",
            "language": "Greek",
            "verseNum": 31,
            "cueNdx": 31,
            "cueTime": 281146,
            "cueText": " καὶ δευτέρα ὁμοία, αὕτη ἀγαπήσεις τὸν πλησίον σου ὡς σεαυτόν μείζων τούτων ἄλλη ἐντολὴ οὐκ ἔστι\r\n"
        },
        {
            "testament": "NT",
            "book": "Mark",
            "chapter": "12",
            "textSrc": "GOC",
            "language": "Greek",
            "verseNum": 32,
            "cueNdx": 32,
            "cueTime": 289685,
            "cueText": " καὶ εἶπεν αὐτῷ ὁ γραμματεύς καλῶς, διδάσκαλε, ἐπ᾽ ἀληθείας εἶπας ὅτι εἷς ἐστι καὶ οὐκ ἔστιν ἄλλος πλὴν αὐτοῦ\r\n"
        },
        {
            "testament": "NT",
            "book": "Mark",
            "chapter": "12",
            "textSrc": "GOC",
            "language": "Greek",
            "verseNum": 33,
            "cueNdx": 33,
            "cueTime": 297727,
            "cueText": " καὶ τὸ ἀγαπᾷν αὐτὸν ἐξ ὅλης τῆς καρδίας καὶ ἐξ ὅλης τῆς συνέσεως καὶ ἐξ ὅλης τῆς ψυχῆς καὶ ἐξ ὅλης τῆς ἰσχύος, καὶ τὸ ἀγαπᾶν τὸν πλησίον ὡς ἑαυτὸν πλεῖόν ἐστι πάντων τῶν ὁλοκαυτωμάτων καὶ θυσιῶν\r\n"
        },
        {
            "testament": "NT",
            "book": "Mark",
            "chapter": "12",
            "textSrc": "GOC",
            "language": "Greek",
            "verseNum": 34,
            "cueNdx": 34,
            "cueTime": 311612,
            "cueText": " καὶ ὁ Ἰησοῦς ἰδὼν ὅτι νουνεχῶς ἀπεκρίθη, εἶπεν αὐτῷ οὐ μακρὰν εἶ ἀπὸ τῆς βασιλείας τοῦ Θεοῦ καὶ οὐδεὶς οὐκέτι ἐτόλμα αὐτὸν ἐπερωτῆσαι\r\n"
        },
        {
            "testament": "NT",
            "book": "Mark",
            "chapter": "12",
            "textSrc": "GOC",
            "language": "Greek",
            "verseNum": 35,
            "cueNdx": 35,
            "cueTime": 323546,
            "cueText": " Καὶ ἀποκριθεὶς ὁ Ἰησοῦς ἔλεγε διδάσκων ἐν τῷ ἱερῷ πῶς λέγουσιν οἱ γραμματεῖς ὅτι ὁ Χριστὸς υἱὸς Δαυΐδ ἐστι;\r\n"
        },
        {
            "testament": "NT",
            "book": "Mark",
            "chapter": "12",
            "textSrc": "GOC",
            "language": "Greek",
            "verseNum": 36,
            "cueNdx": 36,
            "cueTime": 331748,
            "cueText": " αὐτὸς γὰρ Δαυῒδ εἶπεν ἐν Πνεύματι Ἁγίῳ λέγει ὁ Κύριος τῷ Κυρίῳ μου, κάθου ἐκ δεξιῶν μου ἕως ἂν θῶ τοὺς ἐχθρούς σου ὑποπόδιον τῶν ποδῶν σου\r\n"
        },
        {
            "testament": "NT",
            "book": "Mark",
            "chapter": "12",
            "textSrc": "GOC",
            "language": "Greek",
            "verseNum": 37,
            "cueNdx": 37,
            "cueTime": 345612,
            "cueText": " αὐτὸς οὖν Δαυῒδ λέγει αὐτὸν Κύριον καὶ πόθεν υἱὸς αὐτοῦ ἐστι; καὶ ὁ πολὺς ὄχλος ἤκουεν αὐτοῦ ἡδέως\r\n"
        },
        {
            "testament": "NT",
            "book": "Mark",
            "chapter": "12",
            "textSrc": "GOC",
            "language": "Greek",
            "verseNum": 38,
            "cueNdx": 38,
            "cueTime": 354919,
            "cueText": " Καὶ ἔλεγεν αὐτοῖς ἐν τῇ διδαχῇ αὐτοῦ βλέπετε ἀπὸ τῶν γραμματέων τῶν θελόντων ἐν στολαῖς περιπατεῖν καὶ ἀσπασμοὺς ἐν ταῖς ἀγοραῖς\r\n"
        },
        {
            "testament": "NT",
            "book": "Mark",
            "chapter": "12",
            "textSrc": "GOC",
            "language": "Greek",
            "verseNum": 39,
            "cueNdx": 39,
            "cueTime": 364076,
            "cueText": " καὶ πρωτοκαθεδρίας ἐν ταῖς συναγωγαῖς καὶ πρωτοκλισίας ἐν τοῖς δείπνοις\r\n"
        },
        {
            "testament": "NT",
            "book": "Mark",
            "chapter": "12",
            "textSrc": "GOC",
            "language": "Greek",
            "verseNum": 40,
            "cueNdx": 40,
            "cueTime": 368955,
            "cueText": " οἱ κατεσθίοντες τὰς οἰκίας τῶν χηρῶν καὶ προφάσει μακρὰ προσευχόμενοι οὗτοι λήψονται περισσότερον κρῖμα\r\n"
        },
        {
            "testament": "NT",
            "book": "Mark",
            "chapter": "12",
            "textSrc": "GOC",
            "language": "Greek",
            "verseNum": 41,
            "cueNdx": 41,
            "cueTime": 377887,
            "cueText": " Καὶ καθίσας ὁ Ἰησοῦς κατέναντι τοῦ γαζοφυλακίου ἐθεώρει πῶς ὁ ὄχλος βάλλει χαλκὸν εἰς τὸ γαζοφυλάκιον καὶ πολλοὶ πλούσιοι ἔβαλλον πολλά\r\n"
        },
        {
            "testament": "NT",
            "book": "Mark",
            "chapter": "12",
            "textSrc": "GOC",
            "language": "Greek",
            "verseNum": 42,
            "cueNdx": 42,
            "cueTime": 386510,
            "cueText": " καὶ ἐλθοῦσα μία χήρα πτωχὴ ἔβαλε λεπτὰ δύο, ὅ ἐστι κοδράντης\r\n"
        },
        {
            "testament": "NT",
            "book": "Mark",
            "chapter": "12",
            "textSrc": "GOC",
            "language": "Greek",
            "verseNum": 43,
            "cueNdx": 43,
            "cueTime": 395893,
            "cueText": " καὶ προσκαλεσάμενος τοὺς μαθητὰς αὐτοῦ εἶπεν αὐτοῖς ἀμὴν λέγω ὑμῖν ὅτι ἡ χήρα ἡ πτωχὴ αὕτη πλεῖον πάντων ἔβαλε τῶν βαλλόντων εἰς τὸ γαζοφυλάκιον\r\n"
        },
        {
            "testament": "NT",
            "book": "Mark",
            "chapter": "12",
            "textSrc": "GOC",
            "language": "Greek",
            "verseNum": 44,
            "cueNdx": 44,
            "cueTime": 408352,
            "cueText": " πάντες γὰρ ἐκ τοῦ περισσεύοντος αὐτοῖς ἔβαλον αὕτη δὲ ἐκ τῆς ὑστερήσεως αὐτῆς πάντα ὅσα εἶχεν ἔβαλεν, ὅλον τὸν βίον αὐτῆς "
        }
    ]
}